speakerlab/__init__.py
speakerlab/bin/__init__.py
speakerlab/bin/compute_score_metrics.py
speakerlab/bin/export_speaker_embedding_onnx.py
speakerlab/bin/extract.py
speakerlab/bin/extract_ssl.py
speakerlab/bin/infer_diarization.py
speakerlab/bin/infer_sv.py
speakerlab/bin/infer_sv_batch.py
speakerlab/bin/infer_sv_ssl.py
speakerlab/bin/train.py
speakerlab/bin/train_asd.py
speakerlab/bin/train_para.py
speakerlab/bin/train_rdino.py
speakerlab/bin/train_sdpn.py
speakerlab/dataset/__init__.py
speakerlab/dataset/dataset.py
speakerlab/dataset/dataset_asd.py
speakerlab/dataset/dataset_rdino.py
speakerlab/dataset/dataset_sdpn.py
speakerlab/loss/__init__.py
speakerlab/loss/dino_loss.py
speakerlab/loss/keleo_loss.py
speakerlab/loss/margin_loss.py
speakerlab/loss/sdpn_loss.py
speakerlab/models/__init__.py
speakerlab/models/campplus/DTDNN.py
speakerlab/models/campplus/__init__.py
speakerlab/models/campplus/classifier.py
speakerlab/models/campplus/layers.py
speakerlab/models/ecapa_tdnn/ECAPA_TDNN.py
speakerlab/models/ecapa_tdnn/__init__.py
speakerlab/models/eres2net/ERes2Net.py
speakerlab/models/eres2net/ERes2NetV2.py
speakerlab/models/eres2net/ERes2Net_huge.py
speakerlab/models/eres2net/__init__.py
speakerlab/models/eres2net/fusion.py
speakerlab/models/eres2net/pooling_layers.py
speakerlab/models/rdino/ECAPA_TDNN.py
speakerlab/models/rdino/RDINO_Head.py
speakerlab/models/rdino/__init__.py
speakerlab/models/rdino/combiner.py
speakerlab/models/res2net/Res2Net.py
speakerlab/models/res2net/__init__.py
speakerlab/models/resnet/ResNet.py
speakerlab/models/resnet/__init__.py
speakerlab/models/sdpn/ECAPA_TDNN.py
speakerlab/models/sdpn/SDPN_Head.py
speakerlab/models/sdpn/__init__.py
speakerlab/models/sdpn/combiner.py
speakerlab/models/talknet/__init__.py
speakerlab/models/talknet/attentionLayer.py
speakerlab/models/talknet/audioEncoder.py
speakerlab/models/talknet/talknet.py
speakerlab/models/talknet/visualEncoder.py
speakerlab/models/xvector/TDNN.py
speakerlab/models/xvector/__init__.py
speakerlab-0.0.6.dist-info/licenses/LICENSE
speakerlab-0.0.6.dist-info/METADATA
speakerlab-0.0.6.dist-info/WHEEL
speakerlab-0.0.6.dist-info/top_level.txt
speakerlab-0.0.6.dist-info/RECORD
