Metadata-Version: 2.4
Name: speakerlab
Version: 0.0.6
Summary: 3D-Speaker is an open-source toolkit for single- and multi-modal speaker verification, speaker recognition, and speaker diarization.
Author-email: WEA <8200880126@stu.hit.edu.cn>
License-Expression: Apache-2.0
Project-URL: Homepage, https://github.com/W-E-A/3D-Speaker
Project-URL: Repository, https://github.com/W-E-A/3D-Speaker
Classifier: Programming Language :: Python :: 3
Classifier: Operating System :: OS Independent
Requires-Python: >=3.8
License-File: LICENSE
Requires-Dist: torch>=1.10.1
Requires-Dist: torchaudio>=0.10.1
Requires-Dist: torchvision
Requires-Dist: tqdm>=4.42.0
Requires-Dist: scipy>=1.7.0
Requires-Dist: numpy<2.0,>=1.20.0
Requires-Dist: scikit-learn>=1.0.2
Requires-Dist: datasets<=3.6.0,>=3.0.0
Requires-Dist: funasr>=1.2.6
Requires-Dist: modelscope>=1.28.0
Requires-Dist: transformers
Requires-Dist: matplotlib
Requires-Dist: pandas
Requires-Dist: openpyxl
Requires-Dist: textgrid
Requires-Dist: python_speech_features
Requires-Dist: hdbscan
Requires-Dist: fastcluster
Dynamic: license-file
